setup.cfg
setup.py
repoze/__init__.py
repoze.what.plugins.ip.egg-info/PKG-INFO
repoze.what.plugins.ip.egg-info/SOURCES.txt
repoze.what.plugins.ip.egg-info/dependency_links.txt
repoze.what.plugins.ip.egg-info/namespace_packages.txt
repoze.what.plugins.ip.egg-info/not-zip-safe
repoze.what.plugins.ip.egg-info/requires.txt
repoze.what.plugins.ip.egg-info/top_level.txt
repoze/what/__init__.py
repoze/what/plugins/__init__.py
repoze/what/plugins/ip/__init__.py
repoze/what/plugins/ip/ip_from.py
repoze/what/plugins/ip/ipaddr.py
tests/__init__.py
tests/test_predicates.py