Metadata-Version: 1.0
Name: repoze.what.plugins.ip
Version: 0.2
Summary: ip based restrictions for repoze.what.
Home-page: http://code.google.com/p/repoze-what-plugins-ip
Author: Vince Spicer
Author-email: vinces1979@gmail.com
License: Apache 2.0
Keywords: wsgi repoze what paste paster google ip ipaddr proxy
Platform: UNKNOWN
